stinder/__init__.py
stinder/__main__.py
stinder/home.py
stinder/login.py
stinder/match.py
stinder/stinder_images_rc.py
stinder/users.db
stinder/resources/stinder_images.qrc
stinder/resources/fonts/Nexa Light.otf
stinder/resources/fonts/NexaBlack.otf
stinder/resources/fonts/NexaBlackItalic.otf
stinder/resources/fonts/NexaBold.otf
stinder/resources/fonts/NexaBoldItalic.otf
stinder/resources/fonts/NexaBook.otf
stinder/resources/fonts/NexaBookItalic.otf
stinder/resources/fonts/NexaHeavy.otf
stinder/resources/fonts/NexaHeavyItalic.otf
stinder/resources/fonts/NexaLight.otf
stinder/resources/fonts/NexaLightItalic.otf
stinder/resources/fonts/NexaRegular.otf
stinder/resources/fonts/NexaRegularItalic.otf
stinder/resources/fonts/NexaThin.otf
stinder/resources/fonts/NexaThinItalic.otf
stinder/resources/fonts/NexaXBold.otf
stinder/resources/fonts/NexaXBoldItalic.otf
stinder/resources/fonts/Nexa_Bold.otf
stinder/resources/images/AD-profile.png
stinder/resources/images/IMG_4845.JPG
stinder/resources/images/ce-profile.jpg
stinder/resources/images/eg_pfp.jpg
stinder/resources/images/stinder_book_logo.png
stinder/resources/images/stinder_logo.png
stinder/resources/images/wt-profile.png
stinder-0.3.3.dist-info/METADATA
stinder-0.3.3.dist-info/WHEEL
stinder-0.3.3.dist-info/entry_points.txt
stinder-0.3.3.dist-info/top_level.txt
stinder-0.3.3.dist-info/RECORD
