Metadata-Version: 2.1
Name: stinder
Version: 0.3.3
Summary: The Stinder project aims to help students find compatible study partners through their major and coursework for optimal study sessions.
Home-page: https://github.com/gibbons-eddie/Stinder
Author: Eddie Gibbons, Allison Denham, Carlos Echenique, Wyatt Townsend, Yuchen Xiong
License: UNKNOWN
Platform: UNKNOWN
Classifier: Development Status :: 3 - Alpha
Classifier: License :: OSI Approved :: MIT License
Classifier: Programming Language :: Python :: 3
Requires-Python: >=3.8.2
Requires-Dist: numpy (>=1.21.0)
Requires-Dist: PySide6 (>=6.1.1)
